langchain_exa-0.3.1.dist-info/METADATA
langchain_exa-0.3.1.dist-info/WHEEL
langchain_exa-0.3.1.dist-info/entry_points.txt
langchain_exa-0.3.1.dist-info/licenses/LICENSE
langchain_exa/__init__.py
langchain_exa/_utilities.py
langchain_exa/py.typed
langchain_exa/retrievers.py
langchain_exa/tools.py
langchain_exa-0.3.1.dist-info/RECORD
