Metadata-Version: 2.1
Name: langchain-exa
Version: 0.3.1
Summary: An integration package connecting Exa and LangChain
License: MIT
Project-URL: Source Code, https://github.com/langchain-ai/langchain/tree/master/libs/partners/exa
Project-URL: Release Notes, https://github.com/langchain-ai/langchain/releases?q=tag%3A%22langchain-exa%3D%3D0%22&expanded=true
Project-URL: repository, https://github.com/langchain-ai/langchain
Requires-Python: >=3.9
Requires-Dist: langchain-core<1.0.0,>=0.3.76
Requires-Dist: exa-py<2.0.0,>=1.0.8
